Workbook

Sheet ROI Calculator
A2: Veeam Data Cloud for Microsoft 365
A3: Risk & ROI Calculator | ASEAN & South Korea
A4: Fill in the yellow-highlighted cells below. All other cells are calculated automatically.
B7: ▌ STEP 1 — CUSTOMER PROFILE
B8: Organisation / Business Unit | D8: Optional — used to personalise the report
B9: Country | C9: Singapore | D9: Select from dropdown ▾ (Singapore · Indonesia · Thailand · Philippines · Malaysia · South Korea)
B10: Industry | C10: Financial | D10: Select from dropdown ▾ (Financial · Healthcare · Legal · Tech · Retail · Manufacturing · Other)
B11: Number of M365 Users | C11: 5000 | D11: Total licensed M365 users (mailboxes + Teams + SharePoint)
B12: Annual Revenue (USD) | C12: USD 50M – 500M | D12: Select from dropdown ▾ (Under USD 50M · USD 50M–500M · USD 500M–2B · USD 2B–10B · Over USD 10B)
B13: Veeam Quote — Total Annual (USD) | D13: Optional — enter your TOTAL annual quote (tax-inclusive). Leave blank to use indicative estimate of USD 88.20/user/yr + local tax for VDC Premium tier.
B14: Prior M365 data loss incident? | C14: No | D14: Applies recurrence rate to probability of data loss
B15: ▌ STEP 2 — KEY ASSUMPTIONS (blue cells are editable — regulatory fines, tax rates & country data editable in the 'Assumptions' sheet)
B16: Base annual probability of M365 data loss | C16: 0.35 | D16: Sophos State of Ransomware 2024 + Veeam DPTP 2025; covers ransomware, accidental deletion, insider threats & sync corruption
B17: Prior incident recurrence multiplier | C17: 1.65 | D17: Applied only when 'Prior incident = Yes' (see Step 1). Coveware Q4 2023 — 78% recurrence rate among orgs that experienced an attack
B18: Affected users (% of total) | C18: 0.7 | D18: Microsoft Work Trend Index 2024 — 70% of M365 users have primary workflow dependency
B19: Recovery period without Veeam (days) | C19: 15 | D19: Coveware Q4 2023 — median 22 days for full ransomware; 15 days for M365-specific scenarios. Productivity is modelled as a decay curve (Days 1–2: 90% impaired → Days 3–7: 50% → Days 8–15: 20%), giving ~39% effective loss factor.
B20: Base VDC price per user per year (USD) | C20: 88.2 | D20: Indicative assessment of USD 88.20/user/yr for Veeam Data Cloud for M365 — VDC Premium tier. Actual price may vary. Contact Veeam for a formal quote.
B23: ▌ STEP 3 — RISK EXPOSURE BREAKDOWN
B24: Component | C24: Formula Basis | D24: Value (USD) | E24: Source
B25: Productivity loss | C25: Affected users × avg. daily wage × phased recovery: Days 1–2 @ 90% impaired, Days 3–7 @ 50%, Days 8–15 @ 20% (≈39% effective loss factor vs flat 100%) | D25: =ROUND(C11*C18,0)*Assumptions!C5*(MIN(2,C19)*0.9+MAX(0,MIN(5,C19-2))*0.5+MAX(0,C19-7)*0.2) | E25: Phased decay model — Days 1–2: 90% impaired (Coveware Q4 2023: immediate disruption); Days 3–7: 50% impaired (partial workarounds); Days 8–15: 20% impaired (progressive restoration). Effective lost days: 5.9 of 15. Microsoft Work Trend Index 2024 (70% M365 dependency); ILO Global Wage Report 2024.
B26: IT recovery & professional services | C26: Base USD 15,000 + per-user component (scaled by org size) | D26: =15000+C11*IF(C11>1000,35,50) | E26: Veeam Ransomware Trends Report 2024
B27: Regulatory fine exposure (risk-weighted) | C27: Gross statutory fine × enforcement probability | D27: =IF(Assumptions!C13=1,Assumptions!C20*Assumptions!C10,IF(Assumptions!C9>0,Assumptions!C20*Assumptions!C9,Assumptions!C8))*Assumptions!C11 | E27: Country data protection regulation (see Ref sheet)
B28: Customer impact exposure (risk-weighted) | C28: Annual revenue × industry customer-impact factor (lost-business proxy) | D28: =Assumptions!C20*Assumptions!C22 | E28: IBM Cost of a Data Breach 2024 (Ponemon Institute) — 'lost business' component ~$1.47M globally per breach. Industry factors as % of annual revenue.
B29: Total estimated cost — single incident | C29: Sum of all four components above | D29: =D25+D26+D27+D28
B30: RISK-ADJUSTED ANNUAL EXPOSURE (without Veeam) | C30: Total incident cost × effective annual probability | D30: =D29*Assumptions!C14
B32: ▌ STEP 4 — VEEAM VDC INVESTMENT & PROTECTION RATIO
B33: VDC annual base cost (before tax) | C33: Users × effective price per user (quote backed out of tax-inclusive total) | D33: =C11*Assumptions!C15
B34: Local tax (applied per country) | C34: =CONCATENATE(Assumptions!C7," applied on base cost") | D34: =D33*Assumptions!C6
B35: TOTAL ANNUAL COST OF VEEAM VDC (incl. tax) | C35: Base cost + local tax | D35: =D33+D34
B37: PROTECTION RATIO | C37: Risk-adjusted exposure ÷ Veeam annual cost | D37: =IFERROR(D30/D35,0)
B38: Expected annual loss avoidance (probability-weighted) | C38: Risk-adjusted annual exposure minus Veeam annual cost — an expected value, not a guaranteed saving | D38: =D30-D35
B39: Return on investment (expected value basis) | C39: Net expected value as % of Veeam investment | D39: =IFERROR((D30-D35)/D35,0)
B41: ▌ SUMMARY
B42: ="Annual risk exposure: "&TEXT(D30,"$#,##0")&" · Veeam annual cost: "&TEXT(D35,"$#,##0")&" · Protection ratio: "&TEXT(D37,"0.0")&"× (every $1 invested covers $"&TEXT(D37,"0.0")&" of risk exposure) · Net expected annual savings: "&TEXT(D38,"$#,##0")&IF(D37<1," ⚠ Protection ratio below 1.0× at this org size — consider requesting a volume-adjusted Veeam quote.",".")
B43: =C9&" · "&C10&" · "&TEXT(C11,"#,##0")&" M365 users · "&TEXT(Assumptions!C14,"0.0%")&" effective annual incident probability"&CHAR(10)&"Customer impact ("&TEXT(Assumptions!C22,"0.0%")&" of annual revenue): "&TEXT(D28,"$#,##0")&" — IBM Cost of a Data Breach 2024 (Ponemon), 'lost business' component"
B46: ⚠ This workbook is an illustrative presales tool. All figures are modelled estimates derived from published third-party research and publicly available regulatory frameworks. Actual costs, probabilities, and penalties will vary by organisation. This tool does not constitute legal, financial, or compliance advice. © Veeam Software

Sheet Assumptions
A2: Calculations — Lookup Values (auto-derived from your inputs on ROI Calculator)
B4: Derived Variable | C4: Value | E4: Source / Note
B5: Avg daily wage — selected country (USD) | C5: =IFERROR(VLOOKUP('ROI Calculator'!C9,Ref!B:I,2,0),55) | E5: ILO Global Wage Report 2024 — knowledge-worker rate for selected country
B6: Local tax rate | C6: =IFERROR(VLOOKUP('ROI Calculator'!C9,Ref!B:I,3,0),0.09) | E6: Country VAT/GST rate applied to Veeam VDC subscription cost
B7: Tax label | C7: =IFERROR(VLOOKUP('ROI Calculator'!C9,Ref!B:I,4,0),"GST 9%") | E7: Display label for the applicable tax
B8: PDPA / fixed fine cap (USD) | C8: =IFERROR(VLOOKUP('ROI Calculator'!C9,Ref!B:I,5,0),740000) | E8: Applies when revenue-based fine % = 0 (e.g. SG PDPA ≈ SGD 1M, TH THB 5M, PH PHP 5M, MY MYR 500K)
B9: Revenue-based fine % (where applicable) | C9: =IFERROR(VLOOKUP('ROI Calculator'!C9,Ref!B:I,6,0),0) | E9: Applies for ID (2% of revenue) and KR (3% of revenue). Zero = use fixed cap instead.
B10: MAS fine % — SG financial entities only | C10: =IFERROR(VLOOKUP('ROI Calculator'!C9,Ref!B:I,7,0),0) | E10: MAS Technology Risk Management Guidelines 2021: up to 10% of annual turnover (SG financial only)
B11: Regulatory enforcement probability | C11: =IFERROR(VLOOKUP('ROI Calculator'!C9,Ref!B:I,8,0),0.35) | E11: Probability that a breach results in regulatory action — calibrated per regulator's enforcement track record
B12: Industry risk multiplier | C12: =IFERROR(VLOOKUP('ROI Calculator'!C10,Ref!K:L,2,0),1) | E12: Financial 1.4×, Healthcare 1.3×, Legal 1.2×, Tech/Retail 1.1×, Manufacturing/Other 1.0×
B13: MAS applicability flag (1 = yes, 0 = no) | C13: =IF(AND('ROI Calculator'!C9="Singapore",'ROI Calculator'!C10="Financial"),1,0) | E13: Triggers MAS 10%-of-turnover penalty instead of PDPA fixed cap when SG + financial
B14: Effective annual incident probability | C14: =C16*(IF(OR('ROI Calculator'!C14="Yes",'ROI Calculator'!C14="I'm Not Sure"),C17,1))*C12 | D14: If 'Yes' or 'I'm Not Sure': applies the 1.65× prior-incident recurrence multiplier (Coveware Q4 2023 — 78% recurrence rate among orgs that experienced an attack). Default 'No' uses base probability only. | E14: Base probability × prior-incident recurrence multiplier × industry risk multiplier
B15: Effective VDC price per user per year (USD) | C15: =IF(ISNUMBER('ROI Calculator'!C13),('ROI Calculator'!C13/(1+C6))/'ROI Calculator'!C11,'ROI Calculator'!C20) | E15: Uses customer quote (C13) if provided — treated as tax-inclusive total; backs out local tax rate to derive base per-user cost. Otherwise uses indicative estimate.
B16: Base annual probability of M365 data loss | C16: ='ROI Calculator'!C16 | E16: Mirrors editable assumption from ROI Calculator (Step 2)
B17: Prior incident recurrence multiplier (applied if 'Yes' in Step 1) | C17: ='ROI Calculator'!C17 | E17: Mirrors editable assumption from ROI Calculator (Step 2)
B18: Affected users (% of M365 user base) | C18: ='ROI Calculator'!C18 | E18: Mirrors editable assumption from ROI Calculator (Step 2)
B19: Recovery period without Veeam (days) | C19: ='ROI Calculator'!C19 | E19: Mirrors editable assumption from ROI Calculator (Step 2)
B20: Annual revenue (USD) — converted from band | C20: =IFERROR(VLOOKUP('ROI Calculator'!C12,Ref!S:T,2,0),275000000) | D20: Override: type an exact USD figure directly into C20 if precise revenue is known. This replaces the band mid-point and flows through all revenue-sensitive calculations (regulatory fine, customer impact exposure).
B21: ⓘ Rows 16-19 mirror editable assumptions from the ROI Calculator (Step 2). All other rows are derived from country/industry selections and the Ref sheet.
B22: Industry customer-impact factor (% of revenue) | C22: =IFERROR(VLOOKUP('ROI Calculator'!C10,Ref!K:M,3,0),0.005) | D22: Ponemon/IBM Cost of a Data Breach 2024 — lost-business component, expressed as % of annual revenue. Default 0.5% if industry not matched.

Sheet Ref
A1: Code | B1: Country | C1: Avg Daily Wage (USD) | D1: Local Tax Rate | E1: Tax Label | F1: PDPA / Fixed Fine Cap (USD) (applies when Fine % = 0) | G1: Revenue-Based Fine % (overrides cap when > 0) | H1: MAS Fine % of Revenue (SG financial entities only) | I1: Enforcement Probability | J1: Fine Calculation Logic | K1: Industry Key | L1: Risk Multiplier | M1: Customer Impact Factor (IBM 2024) | N1: Country | O1: Industry | P1: Regulation | Q1: Key Penalty | R1: Notes | S1: Revenue Band | T1: Midpoint (USD)
A2: SG | B2: Singapore | C2: 276 | D2: 0.09 | E2: GST 9% | F2: 740000 | G2: 0 | H2: 0.1 | I2: 0.35 | J2: Non-financial: PDPA cap SGD 1M (≈ USD 740K) × 35% enforcement Financial (MAS): 10% of annual turnover × 35% enforcement | K2: Financial | L2: 1.4 | M2: 0.01 | N2: SG | O2: All industries | P2: PDPA (amended 2021) | Q2: Max SGD 1,000,000 | R2: PDPC issued fines of up to SGD 1M for data breaches. Breach notification mandatory within 3 days of assessing incident as notifiable. | S2: Under USD 50M | T2: 25000000
A3: ID | B3: Indonesia | C3: 53 | D3: 0.11 | E3: PPN/VAT 11% | F3: 0 | G3: 0.02 | H3: 0 | I3: 0.2 | J3: Revenue-based: 2% of annual revenue × 20% enforcement probability | K3: Healthcare | L3: 1.3 | M3: 0.012 | N3: SG | O3: Financial (MAS-regulated) | P3: MAS Technology Risk Management Guidelines 2021 | Q3: Up to 10% of annual turnover | R3: MAS-regulated entities face revenue-based penalties. Supervisory action and licence implications possible. | S3: USD 50M – 500M | T3: 275000000
A4: TH | B4: Thailand | C4: 83 | D4: 0.07 | E4: VAT 7% | F4: 140000 | G4: 0 | H4: 0 | I4: 0.25 | J4: Fixed cap: THB 5M (≈ USD 140K) × 25% enforcement probability | K4: Legal | L4: 1.2 | M4: 0.008 | N4: ID | O4: All industries | P4: PDP Law No. 27 / 2022 | Q4: Up to 2% of annual revenue | R4: Effective 2024. Enforcement capacity at Kominfo still maturing. Transition period ended Oct 2024. | S4: USD 500M – 2B | T4: 1250000000
A5: PH | B5: Philippines | C5: 50 | D5: 0.12 | E5: VAT 12% | F5: 88000 | G5: 0 | H5: 0 | I5: 0.35 | J5: Fixed cap: PHP 5M (≈ USD 88K) × 35% enforcement probability | K5: Tech | L5: 1.1 | M5: 0.007 | N5: TH | O5: All industries | P5: PDPA B.E. 2562 (2019) | Q5: Criminal fine up to THB 5,000,000 + civil damages | R5: Civil liability may exceed statutory cap. PDPC Thailand actively enforcing since 2022. | S5: USD 2B – 10B | T5: 5500000000
A6: MY | B6: Malaysia | C6: 75 | D6: 0.08 | E6: SST 8% | F6: 107000 | G6: 0 | H6: 0 | I6: 0.25 | J6: Fixed cap: MYR 500K (≈ USD 107K) × 25% enforcement probability | K6: Retail | L6: 1.1 | M6: 0.004 | N6: PH | O6: All industries | P6: Data Privacy Act (RA 10173) | Q6: Admin fine up to PHP 5,000,000 per violation | R6: NPC is one of ASEAN's most active regulators. Imprisonment of responsible officers possible. | S6: Over USD 10B | T6: 15000000000
A7: KR | B7: South Korea | C7: 198 | D7: 0.1 | E7: VAT 10% | F7: 0 | G7: 0.03 | H7: 0 | I7: 0.4 | J7: Revenue-based: 3% of annual turnover × 40% enforcement probability | K7: Manufacturing | L7: 1 | M7: 0.003 | N7: MY | O7: All industries | P7: PDPA 2010 (amended 2024) | Q7: Fine up to MYR 500,000 | R7: 2024 amendments introduced mandatory breach notification and increased penalties. Enforcement accelerating.
K8: Other | L8: 1 | M8: 0.005 | N8: KR | O8: All industries | P8: PIPA (amended 2023) | Q8: Up to 3% of annual turnover | R8: PIPC is Asia's closest equivalent to GDPR regulator. Near-maximum fines issued against large organisations.
A11: ▌ COUNTRY DATA — REGULATORY FRAMEWORK & SOURCES
A12: Country | B12: Regulation | C12: Fine Mechanism | D12: Enforcement Probability — Source | E12: Wage Source
A13: Singapore | B13: PDPA (2012, amended 2021) + MAS TRM Guidelines | C13: Fixed cap SGD 1M (~USD 740K); MAS: 10% revenue for regulated entities | D13: PDPC enforcement track record 2021–2023; MAS enforcement notices (public). Prob = 35%. | E13: MOM Occupational Wages Survey 2023 — ICT Professionals median SGD 8,150/mo
A14: Indonesia | B14: PDP Law No. 27/2022 (in force Oct 2024) | C14: Up to 2% of annual revenue; enforced by Kominfo/BSSN | D14: Kominfo enforcement capacity still maturing; calibrated at 20% given nascent framework. | E14: BPS SAKERNAS 2023 + Mercer TRS — IDR 18.5M/mo for knowledge workers
A15: Thailand | B15: PDPA B.E. 2562 (2019, enforced 2022) | C15: Fixed max THB 5M (~USD 140K); criminal penalties for intentional breach | D15: PDPC Thailand early enforcement phase; calibrated at 25%. Fines issued from 2023. | E15: NSO Thailand Labour Force Survey 2023 — THB 65,000/mo for professional workers
A16: Philippines | B16: Data Privacy Act of 2012 (RA 10173); NPC enforcement active | C16: Fixed cap ~PHP 5M (~USD 88K) per violation; imprisonment possible for officers | D16: NPC is one of the most active ASEAN regulators. Calibrated at 35% based on case log. | E16: PSA Occupational Wages Survey 2022 — PHP 62,000/mo NCR knowledge workers
A17: Malaysia | B17: PDPA 2010 (amendment bill in progress) | C17: Fixed cap MYR 500K (~USD 107K); amendment expected to raise this materially | D17: PDPC Malaysia enforcement increasing; calibrated at 25%. Amendment will raise prob. | E17: DoSM Salary & Wages Survey 2022 — MYR 7,800/mo for professional/technical workers
A18: South Korea | B18: PIPA (Personal Information Protection Act), amended 2023 | C18: Up to 3% of annual revenue; PIPC fines can be material for large breaches | D18: PIPC most active regulator in ASEAN+KR bloc; enforcement probability 40%. | E18: KOSTAT Survey on Labour Conditions 2023 — KRW 5.8M/mo for knowledge workers
A20: ▌ INDUSTRY FACTORS — SOURCES & RATIONALE
A21: Industry | B21: Risk Multiplier — Source | C21: Customer Impact Factor — Source
A22: Financial | B22: Veeam Ransomware Trends Report 2024 — financial sector 40% higher breach frequency + recovery cost vs average | C22: IBM Cost of a Data Breach 2024: financial services avg breach cost ~$6.1M; lost-business share ~1.0% of sector revenue. MAS-regulated entities face additional trust/churn exposure.
A23: Healthcare | B23: Veeam DPTP 2025 + IBM 2024 — healthcare highest avg breach cost ($9.8M). 30% uplift applied. | C23: IBM 2024: healthcare lost-business component largest of any sector (~1.2% of revenue), driven by patient churn, regulatory sanctions, and reputational damage.
A24: Legal | B24: Veeam Ransomware Trends 2024 — legal sector high sensitivity due to client confidentiality obligations. 20% uplift. | C24: IBM 2024: professional services (legal proxy) lost-business ~0.8% of revenue. High client-switching cost offsets lower avg revenue base.
A25: Tech | B25: Veeam DPTP 2025 — tech sector above-average frequency; 10% uplift vs base. Fast recovery capability partially offsets. | C25: IBM 2024: tech sector lost-business ~0.7% of revenue. High brand sensitivity but customer stickiness moderates churn rate.
A26: Retail | B26: Veeam Ransomware Trends 2024 — retail sector average frequency. 10% uplift applied for POS/supply chain exposure. | C26: IBM 2024: retail lost-business ~0.4% of revenue. High transaction volume but low per-customer relationship depth limits churn cost.
A27: Manufacturing | B27: Veeam DPTP 2025 — manufacturing at industry average. OT/IT separation reduces M365-specific exposure. | C27: IBM 2024: industrial/manufacturing lost-business ~0.3% of revenue. B2B relationships and contract structures limit immediate churn.
A28: Other | B28: Conservative base rate applied; no specific uplift. Default 1.0× multiplier. | C28: IBM 2024: cross-industry default ~0.5% of revenue used as conservative midpoint for unclassified sectors.
A30: ▌ INCIDENT PROBABILITY & PRODUCTIVITY — SOURCES
A31: Base incident probability (35%) | B31: Sophos State of Ransomware Report 2024 + Veeam Data Protection Trends Report 2025. Covers all significant M365 data loss events: ransomware, accidental deletion, insider threat, sync corruption. 35% represents the annual likelihood of an organisation experiencing a material M365 data loss event.
A32: Prior incident recurrence (1.65×) | B32: Coveware Ransomware Marketplace Report Q4 2023. 78% of organisations that experienced a ransomware event faced recurrence within 12 months. Multiplier = 1 + (0.78 − 0.35) / 0.35 ≈ 1.65× elevation of base probability.
A33: Affected users (70%) | B33: Microsoft Work Trend Index 2024. ~70% of enterprise M365 users have primary workflow dependency on M365 workloads (Exchange, Teams, SharePoint/OneDrive) as their core productivity environment.
A34: Recovery period (15 days) | B34: Coveware Q4 2023 — median 22-day recovery for full ransomware events; 15 days applied for M365-specific scenarios where core infrastructure remains operational and only data workloads require restoration.
A35: Productivity decay curve (Days 1–2: 90%, Days 3–7: 50%, Days 8–15: 20%) | B35: Coveware Q4 2023 (phase durations); Microsoft Work Trend Index 2024 (workflow dependency). Effective loss factor = 5.9 equivalent fully-lost days out of 15 (≈39%). Replaces flat 100% assumption for CFO-defensible modelling.
A36: IT recovery cost (USD 15,000 base + USD 35–50/user) | B36: Veeam Ransomware Trends Report 2024. Base covers IR retainer, forensic investigation, and comms. Per-user component covers remediation, account reset, data restoration labour. Scaled at USD 50/user for orgs ≤1,000 users; USD 35/user for larger orgs (economies of scale).

Sheet Recovery Workflow
A2: Recovery Workflow: Without vs. With Veeam Data Cloud
A3: What happens after an M365 data loss event (ransomware, accidental deletion, insider threat, or sync corruption)?
B5: ❌ WITHOUT VEEAM — UNPROTECTED | E5: ✓ WITH VEEAM DATA CLOUD — PROTECTED
B6: 1 | C6: Incident detected IT team alerted — operations disrupted immediately | E6: 1 | F6: Incident detected IT team alerted — immutable backups cannot be reached by ransomware
B8: 2 | C8: Scope assessment 2–5 days to determine what data was lost and how | E8: 2 | F8: Systems isolated Affected endpoints isolated; backup environment completely unaffected
B10: 3 | C10: Native tools exhausted M365 recycle bin & retention policies insufficient for full recovery | E10: 3 | F10: Portal login Log into Veeam Data Cloud — no specialist skills required
B12: 4 | C12: External forensics engaged 5–10 additional days, uncertain outcome, high cost | E12: 4 | F12: Recovery point identified Full backup history visible; select last known clean state
B14: 5 | C14: Ransom payment considered No guarantee of recovery; flags org as repeat target (78% recurrence) | E14: 5 | F14: Granular restore Mailboxes, files, Teams chats, or full SharePoint sites — any granularity
B16: 6 | C16: Manual data recreation Weeks of lost productivity across all affected users | E16: 6 | F16: Operations restored Users back to work; complete audit trail and chain of custody generated
B18: 7 | C18: Regulatory notification Tight deadlines: 3 days (SG/MAS), 72 hrs (KR PIPA) — clock is running | E18: 7 | F18: Regulator notified Evidence of clean, complete recovery reduces fine exposure significantly
B20: 8 | C20: Investigation & fines Regulatory action, potential fines, reputational and licence damage
B24: 15 – 30+ DAYS | E24: HOURS – 1 DAY
B25: Outcome: uncertain · Cost: unpredictable | E25: Outcome: guaranteed · Cost: zero marginal
B27: ='ROI Calculator'!B52
